oldschool_management_tools/__init__.py
oldschool_management_tools/calendar_integrator.py
oldschool_management_tools/calendar_items/calendar_item.py
oldschool_management_tools/calendar_tools.py
oldschool_management_tools/mgmt_tools_cmd.py
oldschool_management_tools/special_prompts/special_prompts.py
oldschool_management_tools-0.1.11.dist-info/METADATA
oldschool_management_tools-0.1.11.dist-info/WHEEL
oldschool_management_tools-0.1.11.dist-info/entry_points.txt
oldschool_management_tools-0.1.11.dist-info/RECORD
